Metadata-Version: 1.2
Name: eiputil
Version: 0.0.1
Summary: AWS EC2 EIP Utility.
Home-page: https://github.com/sig9org/eiputil
Author: sig9
Author-email: sig9@sig9.org
Maintainer: sig9
Maintainer-email: sig9@sig9.org
License: MIT License
Keywords: AWS,EC2,EIP
Platform: POSIX
Platform: Windows
Platform: Unix
Platform: MacOS
Classifier: Intended Audience :: Developers
Classifier: License :: OSI Approved :: MIT License
Classifier: Natural Language :: Japanese
Classifier: Operating System :: MacOS
Classifier: Operating System :: Microsoft
Classifier: Operating System :: POSIX
Classifier: Operating System :: OS Independent
Classifier: Programming Language :: Python :: 3 :: Only
Classifier: Programming Language :: Python :: 3.8
